README.md
setup.py
neuroscribe/__init__.py
neuroscribe/loss.py
neuroscribe/tensor.py
neuroscribe.egg-info/PKG-INFO
neuroscribe.egg-info/SOURCES.txt
neuroscribe.egg-info/dependency_links.txt
neuroscribe.egg-info/requires.txt
neuroscribe.egg-info/top_level.txt
neuroscribe/backend/__init__.py
neuroscribe/backend/cpu/__init__.py
neuroscribe/backend/cpu/cpu_backend.py
neuroscribe/backend/cpu/mlops.py
neuroscribe/backend/cuda/__init__.py
neuroscribe/backend/cuda/cuda_backend.py
neuroscribe/backend/cuda/mlops.py
neuroscribe/backend/mps/__init__.py
neuroscribe/backend/mps/mlops.py
neuroscribe/backend/mps/mps_backend.py
neuroscribe/nn/__init__.py
neuroscribe/nn/init.py
neuroscribe/nn/modules/__init__.py
neuroscribe/nn/modules/activation.py
neuroscribe/nn/modules/linear.py
neuroscribe/nn/modules/module.py
neuroscribe/optim/__init__.py
neuroscribe/optim/optimizer.py
neuroscribe/optim/sgd.py
test/test_engine.py