Metadata-Version: 2.1
Name: neuroscribe
Version: 0.1.0
Summary: NeuroScribe - a lightweight deep learning framework.
Author: Ghaith Husrieh
Author-email: Ghaith.Husrieh.01@gmail.com
Classifier: Programming Language :: Python :: 3.12
Classifier: Operating System :: OS Independent
Requires-Python: >=3.12
Requires-Dist: numpy==1.26.4
Requires-Dist: cupy-cuda12x==13.0.0
Requires-Dist: fastrlock==0.8.2
